README.txt
TODO.txt
setup.cfg
setup.py
betahaus/__init__.py
betahaus.portlet.maillist.egg-info/PKG-INFO
betahaus.portlet.maillist.egg-info/SOURCES.txt
betahaus.portlet.maillist.egg-info/dependency_links.txt
betahaus.portlet.maillist.egg-info/entry_points.txt
betahaus.portlet.maillist.egg-info/namespace_packages.txt
betahaus.portlet.maillist.egg-info/not-zip-safe
betahaus.portlet.maillist.egg-info/requires.txt
betahaus.portlet.maillist.egg-info/top_level.txt
betahaus/portlet/__init__.py
betahaus/portlet/maillist/__init__.py
betahaus/portlet/maillist/configure.zcml
betahaus/portlet/maillist/maillistportlet.pt
betahaus/portlet/maillist/maillistportlet.py
betahaus/portlet/maillist/version.txt
betahaus/portlet/maillist/i18n/betahaus.portlet.maillist-sv.po
betahaus/portlet/maillist/i18n/generated.pot
betahaus/portlet/maillist/profiles/default/metadata.xml
betahaus/portlet/maillist/profiles/default/portlets.xml
betahaus/portlet/maillist/tests/__init__.py
betahaus/portlet/maillist/tests/base.py
betahaus/portlet/maillist/tests/functional.txt
betahaus/portlet/maillist/tests/test_functional.py
betahaus/portlet/maillist/tests/test_portlet.py
docs/HISTORY.txt
docs/INSTALL.txt
docs/LICENSE.GPL
docs/LICENSE.txt