Metadata-Version: 1.0
Name: betahaus.portlet.maillist
Version: 0.1
Summary: Subscribe or unsubscribe from maillists
Home-page: http://pypi.python.org/pypi/betahaus.portlet.maillist
Author: Martin Lundwall
Author-email: martin@betahaus.net
License: GPL
Platform: UNKNOWN
Classifier: Framework :: Plone
Classifier: Programming Language :: Python
Classifier: Topic :: Software Development :: Libraries :: Python Modules
